ci/transparency/ptag/types/__init__.py
ci/transparency/ptag/types/_meta.py
ci/transparency/ptag/types/ptag.py
ci/transparency/ptag/types/ptag_series.py
civic_transparency_ptag_types-0.2.5.data/data/share/civic-transparency-ptag-spec/CITATION.cff
civic_transparency_ptag_types-0.2.5.data/data/share/civic-transparency-ptag-spec/LICENSE
civic_transparency_ptag_types-0.2.5.data/data/share/civic-transparency-ptag-spec/README.md
civic_transparency_ptag_types-0.2.5.dist-info/licenses/LICENSE
civic_transparency_ptag_types-0.2.5.dist-info/METADATA
civic_transparency_ptag_types-0.2.5.dist-info/WHEEL
civic_transparency_ptag_types-0.2.5.dist-info/top_level.txt
civic_transparency_ptag_types-0.2.5.dist-info/RECORD
