Metadata-Version: 2.4
Name: civic-transparency-ptag-types
Version: 0.2.5
Summary: Typed Python models (Pydantic v2) for the Civic Transparency PTag specification
Author: Civic Interconnect
License-Expression: MIT
Project-URL: Bug Tracker, https://github.com/civic-interconnect/civic-transparency-py-ptag-types/issues
Project-URL: Documentation, https://civic-interconnect.github.io/civic-transparency-py-ptag-types/latest/
Project-URL: Homepage, https://github.com/civic-interconnect/civic-transparency-py-ptag-types
Project-URL: Repository, https://github.com/civic-interconnect/civic-transparency-py-ptag-types
Keywords: civic,transparency,provenance,ptag,types
Classifier: Development Status :: 3 - Alpha
Classifier: Intended Audience :: Developers
Classifier: Intended Audience :: Science/Research
Classifier: Intended Audience :: Education
Classifier: Programming Language :: Python :: 3
Classifier: Programming Language :: Python :: 3 :: Only
Classifier: Programming Language :: Python :: 3.12
Classifier: Programming Language :: Python :: 3.13
Classifier: Topic :: Software Development :: Libraries
Classifier: Topic :: Software Development :: Code Generators
Classifier: Topic :: Software Development :: Quality Assurance
Requires-Python: >=3.12
License-File: LICENSE
Requires-Dist: pydantic>=2.6
Provides-Extra: dev
Requires-Dist: bandit; extra == "dev"
Requires-Dist: build; extra == "dev"
Requires-Dist: civic-transparency-ptag-spec>=0.2.5; extra == "dev"
Requires-Dist: datamodel-code-generator; extra == "dev"
Requires-Dist: defusedxml; extra == "dev"
Requires-Dist: deptry; extra == "dev"
Requires-Dist: jsonschema; extra == "dev"
Requires-Dist: openapi-spec-validator; extra == "dev"
Requires-Dist: orjson; extra == "dev"
Requires-Dist: packaging; extra == "dev"
Requires-Dist: pre-commit; extra == "dev"
Requires-Dist: pyright; extra == "dev"
Requires-Dist: pytest; extra == "dev"
Requires-Dist: pytest-cov; extra == "dev"
Requires-Dist: referencing; extra == "dev"
Requires-Dist: ruff; extra == "dev"
Requires-Dist: validate-pyproject; extra == "dev"
Provides-Extra: docs
Requires-Dist: mkdocs; extra == "docs"
Requires-Dist: mkdocs-gen-files; extra == "docs"
Requires-Dist: mkdocs-git-revision-date-localized-plugin; extra == "docs"
Requires-Dist: mkdocs-include-markdown-plugin; extra == "docs"
Requires-Dist: mkdocs-literate-nav; extra == "docs"
Requires-Dist: mkdocs-material; extra == "docs"
Requires-Dist: mkdocs-static-i18n; extra == "docs"
Requires-Dist: mkdocstrings[python]>=0.18; extra == "docs"
Requires-Dist: mike; extra == "docs"
Dynamic: license-file
